pybet365/__init__.py
pybet365/cli.py
pybet365/client/__init__.py
pybet365/client/client.py
pybet365/client/config.py
pybet365/response/__init__.py
pybet365/response/base.py
pybet365/response/in_play_events.py
pybet365/response/pre_match_odds.py
pybet365/response/result.py
pybet365/response/upcoming_events.py
pybet365-0.1.1.dist-info/AUTHORS.rst
pybet365-0.1.1.dist-info/LICENSE
pybet365-0.1.1.dist-info/METADATA
pybet365-0.1.1.dist-info/WHEEL
pybet365-0.1.1.dist-info/entry_points.txt
pybet365-0.1.1.dist-info/top_level.txt
pybet365-0.1.1.dist-info/RECORD
