Metadata-Version: 2.1
Name: pybet365
Version: 0.1.1
Summary: Python Wrapper for Bet365 API
Home-page: https://github.com/leonkozlowski/pybet365
Author: Leon Kozlowski
Author-email: leonkozlowski@gmail.com
License: MIT license
Keywords: pybet365
Platform: UNKNOWN
Classifier: Development Status :: 2 - Pre-Alpha
Classifier: Intended Audience :: Developers
Classifier: License :: OSI Approved :: MIT License
Classifier: Natural Language :: English
Classifier: Programming Language :: Python :: 3
Classifier: Programming Language :: Python :: 3.6
Classifier: Programming Language :: Python :: 3.7
Classifier: Programming Language :: Python :: 3.8
Requires-Python: >=3.5
Requires-Dist: Click (>=7.0)
Requires-Dist: requests (>=2.24.0)
